poctools/__init__.py
poctools/base.py
poctools/encrypt/__init__.py
poctools/encrypt/hash.py
poctools/ocr/__init__.py
poctools/ocr/config.py
poctools/ocr/ocr.py
tests/__init__.py
tests/test.py
tests/tianmai_weakcipher.py
poctools-0.0.4.dist-info/METADATA
poctools-0.0.4.dist-info/WHEEL
poctools-0.0.4.dist-info/top_level.txt
poctools-0.0.4.dist-info/RECORD
