Metadata-Version: 2.1
Name: poctools
Version: 0.0.4
Summary: poc common tool library
Home-page: https://github.com/yanmengfei/poctools
Author: itmeng
Author-email: yanitmeng@gmail.net
License: UNKNOWN
Platform: UNKNOWN
